kutumbh/__init__.py
kutumbh-0.1.1.dist-info/LICENCE.txt
kutumbh-0.1.1.dist-info/METADATA
kutumbh-0.1.1.dist-info/WHEEL
kutumbh-0.1.1.dist-info/top_level.txt
kutumbh-0.1.1.dist-info/RECORD
